acace_sentiment_analyzer/__init__.py
acace_sentiment_analyzer-0.1.0.dist-info/METADATA
acace_sentiment_analyzer-0.1.0.dist-info/WHEEL
acace_sentiment_analyzer-0.1.0.dist-info/RECORD
